README.rst
setup.py
Twinkerer.egg-info/SOURCES.txt
twinkerer/__init__.py
twinkerer/cmd.py
twinkerer/twitterapi.py
twinkerer/utils.py
twinkerer.egg-info/PKG-INFO
twinkerer.egg-info/SOURCES.txt
twinkerer.egg-info/dependency_links.txt
twinkerer.egg-info/entry_points.txt
twinkerer.egg-info/requires.txt
twinkerer.egg-info/top_level.txt