Metadata-Version: 1.1
Name: Twinkerer
Version: 0.1.0
Summary: tinkerer small extension to use twitter api.
Home-page: https://github.com/attakei/twinkerer
Author: attakei
Author-email: attakei@gmail.com
License: MIT License
Platform: UNKNOWN
Classifier: Programming Language :: Python
Classifier: License :: OSI Approved :: MIT License
Classifier: Operating System :: OS Independent
Classifier: Development Status :: 3 - Alpha
Classifier: Intended Audience :: Developers
Classifier: Topic :: Software Development :: Libraries :: Python Modules
